mpl_flow.py
mpl_flow-1.0.0.dist-info/METADATA
mpl_flow-1.0.0.dist-info/WHEEL
mpl_flow-1.0.0.dist-info/top_level.txt
mpl_flow-1.0.0.dist-info/RECORD
