Metadata-Version: 2.1
Name: mpl-flow
Version: 1.0.0
Summary: Draw flowcharts and more with matplotlib
Home-page: UNKNOWN
Author: Marco Necci
License: MIT License
Platform: UNKNOWN
Requires-Dist: matplotlib
Requires-Dist: numpy
